mpldxf/__init__.py
mpldxf/backend_dxf.py
mpldxf/dxf_colors.py
mpldxf/test_backend_ezdxf.py
mpldxf-1.0.2.dist-info/LICENSE
mpldxf-1.0.2.dist-info/METADATA
mpldxf-1.0.2.dist-info/WHEEL
mpldxf-1.0.2.dist-info/RECORD
