Metadata-Version: 2.3
Name: mpldxf
Version: 1.0.2
Summary: A fork of mpldxf - a matplotlib backend to write DXF drawings. Modified by NGI to handle geotechnical plots
License: MIT
Keywords: matplotlib,DXF,CAD
Author: David Kent
Requires-Python: >=3.12,<4.0
Classifier: License :: OSI Approved :: MIT License
Classifier: Programming Language :: Python :: 3
Classifier: Programming Language :: Python :: 3.12
Classifier: Programming Language :: Python :: 3.13
Requires-Dist: ezdxf (>=1.3,<2.0)
Requires-Dist: matplotlib (>=3.9.2,<4.0.0)
Requires-Dist: shapely (>=2.0.6,<3.0.0)
Requires-Dist: svgpathtools (>=1.6.1,<2.0.0)
Project-URL: Homepage, https://github.com/norwegian-geotechnical-institute/mpldxf-NGI
Project-URL: Repository, https://github.com/norwegian-geotechnical-institute/mpldxf-NGI
